diaag_nlp_colon/__init__.py
diaag_nlp_colon/classes/__init__.py
diaag_nlp_colon/classes/report.py
diaag_nlp_colon/classes/representations.py
diaag_nlp_colon/components/__init__.py
diaag_nlp_colon/components/colo_keyword_filter.py
diaag_nlp_colon/components/colo_qi_extractor.py
diaag_nlp_colon/components/false_pos_filter.py
diaag_nlp_colon/components/lesion_property_extractor.py
diaag_nlp_colon/components/report_section_filter.py
diaag_nlp_colon/config/__init__.py
diaag_nlp_colon/config/num_words.py
diaag_nlp_colon/config/pipeline_configs.py
diaag_nlp_colon/config/colon/__init__.py
diaag_nlp_colon/config/colon/brat_label_configs.py
diaag_nlp_colon/config/colon/col_patterns.py
diaag_nlp_colon/config/colon/displacy_configs.py
diaag_nlp_colon/config/colon/path_patterns.py
diaag_nlp_colon/config/colon/trained_model_labels.py
diaag_nlp_colon/config/colon/vocab.py
diaag_nlp_colon/nlp_models/__init__.py
diaag_nlp_colon/nlp_models/__pycache__/__init__.cpython-310.pyc
diaag_nlp_colon/nlp_models/en_trained_sections_col/__init__.py
diaag_nlp_colon/nlp_models/en_trained_sections_col/meta.json
diaag_nlp_colon/nlp_models/en_trained_sections_col/__pycache__/__init__.cpython-310.pyc
diaag_nlp_colon/nlp_models/en_trained_sections_col/en_trained_sections_col-2.0.0/README.md
diaag_nlp_colon/nlp_models/en_trained_sections_col/en_trained_sections_col-2.0.0/config.cfg
diaag_nlp_colon/nlp_models/en_trained_sections_col/en_trained_sections_col-2.0.0/meta.json
diaag_nlp_colon/nlp_models/en_trained_sections_col/en_trained_sections_col-2.0.0/tokenizer
diaag_nlp_colon/nlp_models/en_trained_sections_col/en_trained_sections_col-2.0.0/ner/cfg
diaag_nlp_colon/nlp_models/en_trained_sections_col/en_trained_sections_col-2.0.0/ner/model
diaag_nlp_colon/nlp_models/en_trained_sections_col/en_trained_sections_col-2.0.0/ner/moves
diaag_nlp_colon/nlp_models/en_trained_sections_col/en_trained_sections_col-2.0.0/tok2vec/cfg
diaag_nlp_colon-1.2.1.dist-info/licenses/LICENSE
diaag_nlp_colon-1.2.1.dist-info/METADATA
diaag_nlp_colon-1.2.1.dist-info/WHEEL
diaag_nlp_colon-1.2.1.dist-info/top_level.txt
diaag_nlp_colon-1.2.1.dist-info/RECORD
