Metadata-Version: 2.4
Name: diaag_nlp_colon
Version: 1.2.1
Summary: A package for extracting information from Colonoscopy and Colon Pathology reports using Spacy
Author: Emma Peterson
Author-email: Gordon Guyant <flashgordonion@gmail.com>
License: MIT License
Project-URL: Homepage, https://github.com/DIAAG-Health/diaag-nlp-colon
Project-URL: Issues, https://github.com/DIAAG-Health/diaag-nlp-colon/issues
Classifier: Programming Language :: Python :: 3
Classifier: License :: OSI Approved :: MIT License
Classifier: Operating System :: OS Independent
Requires-Python: >=3.7
License-File: LICENSE
Dynamic: license-file
